[
    {
        "id": "fbdc5aeae38a6415",
        "type": "tab",
        "label": "Flow 1",
        "disabled": false,
        "info": "",
        "env": []
    },
    {
        "id": "36ae23ed91dfdeaa",
        "type": "group",
        "z": "fbdc5aeae38a6415",
        "style": {
            "stroke": "#999999",
            "stroke-opacity": "1",
            "fill": "none",
            "fill-opacity": "1",
            "label": true,
            "label-position": "nw",
            "color": "#767676"
        },
        "nodes": [
            "414875922b7d6e4e",
            "49be978a0f12a24b"
        ],
        "x": 1374,
        "y": 639,
        "w": 232,
        "h": 142
    },
    {
        "id": "2dfeb66569eba99c",
        "type": "group",
        "z": "fbdc5aeae38a6415",
        "style": {
            "stroke": "#999999",
            "stroke-opacity": "1",
            "fill": "none",
            "fill-opacity": "1",
            "label": true,
            "label-position": "nw",
            "color": "#767676"
        },
        "nodes": [
            "8b88d180c27180ab",
            "afe179e96ce1b1c1"
        ],
        "x": 54,
        "y": 599,
        "w": 312,
        "h": 122
    },
    {
        "id": "8b854a66fc363cba",
        "type": "udp in",
        "z": "fbdc5aeae38a6415",
        "name": "",
        "iface": "",
        "port": "5005",
        "ipv": "udp4",
        "multicast": "false",
        "group": "",
        "datatype": "utf8",
        "x": 140,
        "y": 180,
        "wires": [
            [
                "cbd3027b8636199a"
            ]
        ]
    },
    {
        "id": "dfc01fdf720bf120",
        "type": "comment",
        "z": "fbdc5aeae38a6415",
        "name": "Recibir mensajes OLED",
        "info": "",
        "x": 180,
        "y": 100,
        "wires": []
    },
    {
        "id": "f7545f5fc5ed5d01",
        "type": "debug",
        "z": "fbdc5aeae38a6415",
        "name": "debug 1",
        "active": true,
        "tosidebar": true,
        "console": false,
        "tostatus": false,
        "complete": "false",
        "statusVal": "",
        "statusType": "auto",
        "x": 1380,
        "y": 400,
        "wires": []
    },
    {
        "id": "cbd3027b8636199a",
        "type": "json",
        "z": "fbdc5aeae38a6415",
        "name": "",
        "property": "payload",
        "action": "",
        "pretty": false,
        "x": 370,
        "y": 180,
        "wires": [
            [
                "cecfbefcfe9ad4eb"
            ]
        ]
    },
    {
        "id": "24ab039d12883d2d",
        "type": "function",
        "z": "fbdc5aeae38a6415",
        "name": "capture_photo",
        "func": "const p = msg.payload || {};\n\nconst sessionId =\n    p.session_id ||\n    p.active_session ||\n    flow.get(\"active_session\") ||\n    \"S01\";\n\nflow.set(\"active_session\", sessionId);\nflow.set(\"session_has_drawing\", p.session_has_drawing === true);\n\nmsg.session_id = sessionId;\nmsg.session_has_drawing = p.session_has_drawing === true;\nmsg.payload = p;\n\nnode.status({\n    fill: \"blue\",\n    shape: \"dot\",\n    text: `Foto ${sessionId}`\n});\n\nreturn msg;",
        "outputs": 1,
        "timeout": 0,
        "noerr": 0,
        "initialize": "",
        "finalize": "",
        "libs": [],
        "x": 920,
        "y": 160,
        "wires": [
            [
                "f7545f5fc5ed5d01",
                "72b564eb3db0739a"
            ]
        ]
    },
    {
        "id": "cecfbefcfe9ad4eb",
        "type": "switch",
        "z": "fbdc5aeae38a6415",
        "name": "",
        "property": "payload.command",
        "propertyType": "msg",
        "rules": [
            {
                "t": "eq",
                "v": "capture_photo",
                "vt": "str"
            },
            {
                "t": "eq",
                "v": "capture_environment",
                "vt": "str"
            },
            {
                "t": "eq",
                "v": "new_session",
                "vt": "str"
            },
            {
                "t": "eq",
                "v": "select_session",
                "vt": "str"
            },
            {
                "t": "eq",
                "v": "generate_drawing",
                "vt": "str"
            },
            {
                "t": "eq",
                "v": "execute_drawing",
                "vt": "str"
            },
            {
                "t": "eq",
                "v": "show_status",
                "vt": "str"
            }
        ],
        "checkall": "true",
        "repair": false,
        "outputs": 7,
        "x": 610,
        "y": 180,
        "wires": [
            [
                "24ab039d12883d2d"
            ],
            [
                "bc9cba9969bad616"
            ],
            [
                "f7cae1dbc726fb38"
            ],
            [
                "f7cae1dbc726fb38"
            ],
            [
                "b2a66ee5b1cd25c8"
            ],
            [
                "f693cd9af1221a54"
            ],
            [
                "43d70ea379b61eb7"
            ]
        ]
    },
    {
        "id": "bc9cba9969bad616",
        "type": "function",
        "z": "fbdc5aeae38a6415",
        "name": "capture_environment",
        "func": "const p = msg.payload || {};\n\nconst sessionId =\n    p.session_id ||\n    p.active_session ||\n    flow.get(\"active_session\") ||\n    \"S01\";\n\nflow.set(\"active_session\", sessionId);\nflow.set(\"session_has_drawing\", p.session_has_drawing === true);\n\nmsg.session_id = sessionId;\nmsg.session_has_drawing = p.session_has_drawing === true;\nmsg.payload = p;\n\nnode.status({\n    fill: \"green\",\n    shape: \"dot\",\n    text: `Ambiente ${sessionId}`\n});\n\nreturn msg;",
        "outputs": 1,
        "timeout": 0,
        "noerr": 0,
        "initialize": "",
        "finalize": "",
        "libs": [],
        "x": 940,
        "y": 220,
        "wires": [
            [
                "f7545f5fc5ed5d01",
                "31956f420c1de013"
            ]
        ]
    },
    {
        "id": "b2a66ee5b1cd25c8",
        "type": "function",
        "z": "fbdc5aeae38a6415",
        "name": "generate_drawing",
        "func": "msg.payload = msg.payload.command;\nreturn msg;",
        "outputs": 1,
        "timeout": 0,
        "noerr": 0,
        "initialize": "",
        "finalize": "",
        "libs": [],
        "x": 930,
        "y": 340,
        "wires": [
            [
                "f7545f5fc5ed5d01",
                "f19e251037337628"
            ]
        ]
    },
    {
        "id": "f693cd9af1221a54",
        "type": "function",
        "z": "fbdc5aeae38a6415",
        "name": "execute_drawing",
        "func": "const p = msg.payload || {};\n\nconst sessionId =\n    p.session_id ||\n    p.active_session ||\n    flow.get(\"active_session\") ||\n    \"S01\";\n\nflow.set(\"active_session\", sessionId);\n\nmsg.session_id = sessionId;\nmsg.payload = p;\n\nnode.status({\n    fill: \"blue\",\n    shape: \"dot\",\n    text: `Ejecutar ${sessionId}`\n});\n\nreturn msg;",
        "outputs": 1,
        "timeout": 0,
        "noerr": 0,
        "initialize": "",
        "finalize": "",
        "libs": [],
        "x": 930,
        "y": 400,
        "wires": [
            [
                "f7545f5fc5ed5d01",
                "ca31b4fae4ded149"
            ]
        ]
    },
    {
        "id": "43d70ea379b61eb7",
        "type": "function",
        "z": "fbdc5aeae38a6415",
        "name": "show_status",
        "func": "msg.payload = msg.payload.command;\nreturn msg;",
        "outputs": 1,
        "timeout": 0,
        "noerr": 0,
        "initialize": "",
        "finalize": "",
        "libs": [],
        "x": 910,
        "y": 460,
        "wires": [
            [
                "f7545f5fc5ed5d01"
            ]
        ]
    },
    {
        "id": "45cbd856808d32bf",
        "type": "debug",
        "z": "fbdc5aeae38a6415",
        "name": "debug 2",
        "active": true,
        "tosidebar": true,
        "console": false,
        "tostatus": false,
        "complete": "false",
        "statusVal": "",
        "statusType": "auto",
        "x": 1400,
        "y": 520,
        "wires": []
    },
    {
        "id": "b20db3363f5101dc",
        "type": "http request",
        "z": "fbdc5aeae38a6415",
        "name": "",
        "method": "use",
        "ret": "bin",
        "paytoqs": "ignore",
        "url": "http://contracam.local/capture",
        "tls": "",
        "persist": false,
        "proxy": "",
        "insecureHTTPParser": false,
        "authType": "",
        "senderr": false,
        "headers": [],
        "x": 370,
        "y": 560,
        "wires": [
            [
                "a5f67b701c90f255"
            ]
        ]
    },
    {
        "id": "72b564eb3db0739a",
        "type": "function",
        "z": "fbdc5aeae38a6415",
        "name": "set_img",
        "func": "const DATA_ROOT = \"/home/pi/data\"; // Cambiar si tu usuario no es pi\n\nconst sessionId =\n    msg.session_id ||\n    msg.payload?.session_id ||\n    msg.payload?.active_session ||\n    flow.get(\"active_session\") ||\n    \"S01\";\n\nflow.set(\"active_session\", sessionId);\n\nconst photoKey = `photo_count_${sessionId}`;\nconst candidateCount = (flow.get(photoKey) || 0) + 1;\n\nconst now = new Date();\nconst stamp = now.toISOString()\n    .replace(/[-:]/g, \"\")\n    .replace(/\\.\\d+Z$/, \"Z\");\n\nconst index = String(candidateCount).padStart(3, \"0\");\n\nmsg.session_id = sessionId;\nmsg.photo_count_candidate = candidateCount;\n\nmsg.url = \"http://contracam.local/capture\";\nmsg.method = \"GET\";\n\nmsg.filename = `${DATA_ROOT}/sessions/${sessionId}/photos/photo_${index}_${stamp}.jpg`;\n\nmsg.payload = null;\n\nnode.status({\n    fill: \"blue\",\n    shape: \"dot\",\n    text: `${sessionId} foto ${index}`\n});\n\nreturn msg;",
        "outputs": 1,
        "timeout": 0,
        "noerr": 0,
        "initialize": "",
        "finalize": "",
        "libs": [],
        "x": 140,
        "y": 560,
        "wires": [
            [
                "b20db3363f5101dc"
            ]
        ]
    },
    {
        "id": "f9bcf92008156283",
        "type": "file",
        "z": "fbdc5aeae38a6415",
        "name": "",
        "filename": "filename",
        "filenameType": "msg",
        "appendNewline": true,
        "createDir": true,
        "overwriteFile": "true",
        "encoding": "none",
        "x": 840,
        "y": 560,
        "wires": [
            [
                "118a90ed1ccfe36e"
            ]
        ]
    },
    {
        "id": "8758becf0fd80834",
        "type": "comment",
        "z": "fbdc5aeae38a6415",
        "name": "Tomar Foto",
        "info": "",
        "x": 150,
        "y": 520,
        "wires": []
    },
    {
        "id": "118a90ed1ccfe36e",
        "type": "function",
        "z": "fbdc5aeae38a6415",
        "name": "respuesta_pantalla",
        "func": "const sessionId =\n    msg.session_id ||\n    flow.get(\"active_session\") ||\n    \"S01\";\n\nconst photoCount =\n    msg.photo_count_candidate ||\n    flow.get(`photo_count_${sessionId}`) ||\n    1;\n\nflow.set(`photo_count_${sessionId}`, photoCount);\nflow.set(\"photo_done\", true);\n\nconst response = {\n    type: \"framework_state\",\n\n    session_id: sessionId,\n\n    photo: true,\n    photo_done: true,\n    photo_count: photoCount,\n\n    step: \"photo\",\n    state: \"done\",\n    message: `Foto ${String(photoCount).padStart(2, \"0\")} guardada`,\n    progress: 25\n};\n\nif (flow.get(\"environment_done\") === true) {\n    response.environment = true;\n    response.environment_done = true;\n}\n\nif (flow.get(\"session_has_drawing\") === true) {\n    response.session_has_drawing = true;\n    response.drawing = true;\n    response.drawing_done = true;\n}\n\nmsg.payload = JSON.stringify(response);\n\nmsg.ip = \"127.0.0.1\";\nmsg.host = \"127.0.0.1\";\nmsg.port = 5006;\n\nnode.status({\n    fill: \"green\",\n    shape: \"dot\",\n    text: `${sessionId} foto ${photoCount}`\n});\n\nreturn msg;",
        "outputs": 1,
        "timeout": 0,
        "noerr": 0,
        "initialize": "",
        "finalize": "",
        "libs": [],
        "x": 1090,
        "y": 560,
        "wires": [
            [
                "414875922b7d6e4e"
            ]
        ]
    },
    {
        "id": "414875922b7d6e4e",
        "type": "udp out",
        "z": "fbdc5aeae38a6415",
        "g": "36ae23ed91dfdeaa",
        "name": "",
        "addr": "127.0.0.1",
        "iface": "",
        "port": "5006",
        "ipv": "udp4",
        "outport": "",
        "base64": false,
        "multicast": "false",
        "x": 1490,
        "y": 740,
        "wires": []
    },
    {
        "id": "0412030552b4690b",
        "type": "comment",
        "z": "fbdc5aeae38a6415",
        "name": "Medir Ambiente",
        "info": "",
        "x": 160,
        "y": 760,
        "wires": []
    },
    {
        "id": "31956f420c1de013",
        "type": "function",
        "z": "fbdc5aeae38a6415",
        "name": "solicitar_lectura_ambiente",
        "func": "const sessionId =\n    msg.session_id ||\n    msg.payload?.session_id ||\n    msg.payload?.active_session ||\n    flow.get(\"active_session\") ||\n    \"S01\";\n\nflow.set(\"active_session\", sessionId);\nflow.set(\"pending_environment_session\", sessionId);\n\nconst toEsp32 = {\n    payload: JSON.stringify({\n        type: \"command\",\n        command: \"read_environment\",\n        source: \"node-red\",\n        target: \"contraenv\",\n        session_id: sessionId,\n        timestamp: new Date().toISOString()\n    }),\n\n    ip: \"contraenv.local\",\n    host: \"contraenv.local\",\n    port: 4210\n};\n\nconst toOled = {\n    payload: JSON.stringify({\n        type: \"status\",\n        session_id: sessionId,\n        step: \"environment\",\n        state: \"running\",\n        message: \"Leyendo ambiente\",\n        progress: 30,\n        environment: false,\n        environment_done: false\n    }),\n\n    ip: \"127.0.0.1\",\n    host: \"127.0.0.1\",\n    port: 5006\n};\n\nreturn [toEsp32, toOled];",
        "outputs": 2,
        "timeout": 0,
        "noerr": 0,
        "initialize": "",
        "finalize": "",
        "libs": [],
        "x": 190,
        "y": 800,
        "wires": [
            [
                "c92a4cf3e53d386a"
            ],
            [
                "414875922b7d6e4e"
            ]
        ],
        "outputLabels": [
            "4210",
            "5006"
        ]
    },
    {
        "id": "c92a4cf3e53d386a",
        "type": "udp out",
        "z": "fbdc5aeae38a6415",
        "name": "",
        "addr": "contraenv.local",
        "iface": "",
        "port": "4210",
        "ipv": "udp4",
        "outport": "",
        "base64": false,
        "multicast": "false",
        "x": 510,
        "y": 760,
        "wires": []
    },
    {
        "id": "8b88d180c27180ab",
        "type": "comment",
        "z": "fbdc5aeae38a6415",
        "g": "2dfeb66569eba99c",
        "name": "Recibir Respuesta de ambiente",
        "info": "",
        "x": 210,
        "y": 640,
        "wires": []
    },
    {
        "id": "afe179e96ce1b1c1",
        "type": "udp in",
        "z": "fbdc5aeae38a6415",
        "g": "2dfeb66569eba99c",
        "name": "",
        "iface": "",
        "port": "5010",
        "ipv": "udp4",
        "multicast": "false",
        "group": "",
        "datatype": "utf8",
        "x": 140,
        "y": 680,
        "wires": [
            [
                "e38712c1cb93a298"
            ]
        ]
    },
    {
        "id": "e38712c1cb93a298",
        "type": "json",
        "z": "fbdc5aeae38a6415",
        "name": "",
        "property": "payload",
        "action": "",
        "pretty": false,
        "x": 430,
        "y": 680,
        "wires": [
            [
                "350768bd95b98620"
            ]
        ]
    },
    {
        "id": "350768bd95b98620",
        "type": "function",
        "z": "fbdc5aeae38a6415",
        "name": "procesar_respuesta_ambiente",
        "func": "const DATA_ROOT = \"/home/pi/data\"; // Cambiar si tu usuario no es pi\n\nconst data = msg.payload;\n\nif (!data || typeof data !== \"object\") {\n    return [null, null];\n}\n\nif (data.type !== \"environment\") {\n    return [null, null];\n}\n\nconst sessionId =\n    data.session_id ||\n    flow.get(\"pending_environment_session\") ||\n    flow.get(\"active_session\") ||\n    \"S01\";\n\nflow.set(\"active_session\", sessionId);\n\n// ----------------------------------------------------\n// Progreso ambiental hacia OLED\n// ----------------------------------------------------\n\nif (data.state === \"running\") {\n    const oledProgress = {\n        payload: JSON.stringify({\n            type: \"status\",\n            session_id: sessionId,\n            step: \"environment\",\n            state: \"running\",\n            message: data.message || \"Leyendo ambiente\",\n            progress: data.progress || 35\n        }),\n        ip: \"127.0.0.1\",\n        host: \"127.0.0.1\",\n        port: 5006\n    };\n\n    return [null, oledProgress];\n}\n\n// ----------------------------------------------------\n// Validar lectura final\n// ----------------------------------------------------\n\nif (data.stage !== \"complete\") {\n    return [null, null];\n}\n\nconst hasTemperature =\n    data.temperature !== null &&\n    data.temperature !== undefined &&\n    !Number.isNaN(Number(data.temperature));\n\nconst hasHumidity =\n    data.humidity !== null &&\n    data.humidity !== undefined &&\n    !Number.isNaN(Number(data.humidity));\n\nconst hasAQI =\n    data.aqi !== null &&\n    data.aqi !== undefined &&\n    !Number.isNaN(Number(data.aqi));\n\nconst hasTVOC =\n    data.tvoc !== null &&\n    data.tvoc !== undefined &&\n    !Number.isNaN(Number(data.tvoc));\n\nconst hasECO2 =\n    data.eco2 !== null &&\n    data.eco2 !== undefined &&\n    !Number.isNaN(Number(data.eco2));\n\nconst hasAllValues =\n    data.state === \"done\" &&\n    data.aht_ok === true &&\n    data.ens_ok === true &&\n    hasTemperature &&\n    hasHumidity &&\n    hasAQI &&\n    hasTVOC &&\n    hasECO2;\n\nif (!hasAllValues) {\n    flow.set(\"environment_done\", false);\n\n    let errorMessage = \"Lectura incompleta\";\n\n    if (data.aht_ok !== true) {\n        errorMessage = \"Error temp/hum\";\n    } else if (data.ens_ok !== true) {\n        errorMessage = \"ENS no estable\";\n    } else if (!hasAQI || !hasTVOC || !hasECO2) {\n        errorMessage = \"Faltan gases\";\n    }\n\n    node.status({\n        fill: \"red\",\n        shape: \"ring\",\n        text: errorMessage\n    });\n\n    const oledError = {\n        payload: JSON.stringify({\n            type: \"status\",\n            session_id: sessionId,\n            environment: false,\n            environment_done: false,\n            step: \"environment\",\n            state: \"error\",\n            message: errorMessage,\n            progress: 35\n        }),\n        ip: \"127.0.0.1\",\n        host: \"127.0.0.1\",\n        port: 5006\n    };\n\n    return [null, oledError];\n}\n\n// ----------------------------------------------------\n// Preparar guardado de lectura válida\n// ----------------------------------------------------\n\nconst envKey = `environment_count_${sessionId}`;\nconst candidateCount = (flow.get(envKey) || 0) + 1;\n\nconst now = new Date();\nconst stamp = now.toISOString()\n    .replace(/[-:]/g, \"\")\n    .replace(/\\.\\d+Z$/, \"Z\");\n\nconst index = String(candidateCount).padStart(3, \"0\");\n\nconst envData = {\n    ok: true,\n\n    session_id: sessionId,\n    index: candidateCount,\n\n    type: data.type,\n    device: data.device || \"contraenv\",\n    hostname: data.hostname || \"contraenv.local\",\n    ip: data.ip || null,\n\n    state: data.state,\n    stage: data.stage,\n    message: data.message || \"Ambiente listo\",\n    progress: data.progress || 50,\n\n    aht_ok: true,\n    ens_ok: true,\n\n    temperature: Number(data.temperature),\n    humidity: Number(data.humidity),\n\n    ens_status: data.ens_status ?? null,\n    aqi: Number(data.aqi),\n    tvoc: Number(data.tvoc),\n    eco2: Number(data.eco2),\n\n    created_at: now.toISOString()\n};\n\nmsg.session_id = sessionId;\nmsg.environment_count_candidate = candidateCount;\nmsg.environment_data = envData;\n\nmsg.filename = `${DATA_ROOT}/sessions/${sessionId}/environment/env_${index}_${stamp}.json`;\nmsg.payload = JSON.stringify(envData, null, 2);\n\nnode.status({\n    fill: \"green\",\n    shape: \"dot\",\n    text: `${sessionId} env ${index}`\n});\n\nreturn [msg, null];",
        "outputs": 2,
        "timeout": 0,
        "noerr": 0,
        "initialize": "",
        "finalize": "",
        "libs": [],
        "x": 650,
        "y": 680,
        "wires": [
            [
                "3d4e32f1372c1a23"
            ],
            [
                "414875922b7d6e4e"
            ]
        ],
        "outputLabels": [
            "write",
            "5006"
        ]
    },
    {
        "id": "49be978a0f12a24b",
        "type": "comment",
        "z": "fbdc5aeae38a6415",
        "g": "36ae23ed91dfdeaa",
        "name": "Enviar a OLED",
        "info": "",
        "x": 1480,
        "y": 680,
        "wires": []
    },
    {
        "id": "f7cae1dbc726fb38",
        "type": "function",
        "z": "fbdc5aeae38a6415",
        "name": "actualizar_sesion_activa",
        "func": "const p = msg.payload || {};\n\nconst sessionId =\n    p.session_id ||\n    p.active_session ||\n    flow.get(\"active_session\") ||\n    \"S01\";\n\nconst hasDrawing = p.session_has_drawing === true;\n\nflow.set(\"active_session\", sessionId);\nflow.set(\"session_has_drawing\", hasDrawing);\n\nmsg.payload = JSON.stringify({\n    type: \"status\",\n    session_id: sessionId,\n    step: \"session\",\n    state: \"done\",\n    message: hasDrawing ? `${sessionId} con dibujo` : `${sessionId} activa`,\n    progress: 0,\n    session_has_drawing: hasDrawing\n});\n\nmsg.ip = \"127.0.0.1\";\nmsg.host = \"127.0.0.1\";\nmsg.port = 5006;\n\nnode.status({\n    fill: \"blue\",\n    shape: \"dot\",\n    text: hasDrawing ? `${sessionId}*` : sessionId\n});\n\nreturn msg;",
        "outputs": 1,
        "timeout": 0,
        "noerr": 0,
        "initialize": "",
        "finalize": "",
        "libs": [],
        "x": 950,
        "y": 280,
        "wires": [
            [
                "414875922b7d6e4e"
            ]
        ]
    },
    {
        "id": "a5f67b701c90f255",
        "type": "function",
        "z": "fbdc5aeae38a6415",
        "name": "validar_foto",
        "func": "\n// Valida que la respuesta de la ESP32CAM sea una imagen JPEG real.\n// Salida 1: foto válida hacia write file.\n// Salida 2: error hacia OLED.\n\nconst sessionId =\n    msg.session_id ||\n    flow.get(\"active_session\") ||\n    \"S01\";\n\nconst payload = msg.payload;\n\nconst isBuffer = Buffer.isBuffer(payload);\nconst size = isBuffer ? payload.length : 0;\n\nconst looksLikeJpeg =\n    isBuffer &&\n    size > 2048 &&\n    payload[0] === 0xFF &&\n    payload[1] === 0xD8 &&\n    payload[2] === 0xFF;\n\nif (!looksLikeJpeg) {\n    node.status({\n        fill: \"red\",\n        shape: \"ring\",\n        text: `Foto inválida ${size} bytes`\n    });\n\n    const oledError = {\n        payload: JSON.stringify({\n            type: \"status\",\n            session_id: sessionId,\n            step: \"photo\",\n            state: \"error\",\n            message: \"Foto invalida\",\n            progress: 20,\n            photo: false,\n            photo_done: false\n        }),\n        ip: \"127.0.0.1\",\n        host: \"127.0.0.1\",\n        port: 5006\n    };\n\n    return [null, oledError];\n}\n\nnode.status({\n    fill: \"green\",\n    shape: \"dot\",\n    text: `Foto OK ${Math.round(size / 1024)} KB`\n});\n\nreturn [msg, null];",
        "outputs": 2,
        "timeout": 0,
        "noerr": 0,
        "initialize": "",
        "finalize": "",
        "libs": [],
        "x": 610,
        "y": 560,
        "wires": [
            [
                "f9bcf92008156283"
            ],
            [
                "414875922b7d6e4e"
            ]
        ],
        "outputLabels": [
            "write",
            "5006"
        ]
    },
    {
        "id": "3d4e32f1372c1a23",
        "type": "file",
        "z": "fbdc5aeae38a6415",
        "name": "",
        "filename": "filename",
        "filenameType": "msg",
        "appendNewline": true,
        "createDir": true,
        "overwriteFile": "true",
        "encoding": "utf8",
        "x": 880,
        "y": 660,
        "wires": [
            [
                "a592552c9a8b24db"
            ]
        ]
    },
    {
        "id": "a592552c9a8b24db",
        "type": "function",
        "z": "fbdc5aeae38a6415",
        "name": "respuesta_ambiente_guardado",
        "func": "const sessionId =\n    msg.session_id ||\n    flow.get(\"active_session\") ||\n    \"S01\";\n\nconst envCount =\n    msg.environment_count_candidate ||\n    flow.get(`environment_count_${sessionId}`) ||\n    1;\n\nflow.set(`environment_count_${sessionId}`, envCount);\nflow.set(\"environment_done\", true);\n\nconst envData = msg.environment_data || {};\nflow.set(\"last_environment\", envData);\n\nconst dataOut = {\n    ...msg,\n    payload: {\n        ...envData,\n        file: msg.filename,\n        environment_count: envCount\n    }\n};\n\nconst oledOut = {\n    payload: JSON.stringify({\n        type: \"framework_state\",\n\n        session_id: sessionId,\n\n        environment: true,\n        environment_done: true,\n        environment_count: envCount,\n\n        step: \"environment\",\n        state: \"done\",\n        message: `Amb ${String(envCount).padStart(2, \"0\")} guardado`,\n        progress: 50\n    }),\n\n    ip: \"127.0.0.1\",\n    host: \"127.0.0.1\",\n    port: 5006\n};\n\nnode.status({\n    fill: \"green\",\n    shape: \"dot\",\n    text: `${sessionId} amb ${envCount}`\n});\n\nreturn [dataOut, oledOut];",
        "outputs": 2,
        "timeout": 0,
        "noerr": 0,
        "initialize": "",
        "finalize": "",
        "libs": [],
        "x": 1110,
        "y": 660,
        "wires": [
            [
                "45cbd856808d32bf"
            ],
            [
                "414875922b7d6e4e"
            ]
        ],
        "outputLabels": [
            "debug",
            "5006"
        ]
    },
    {
        "id": "2cb38bbefe3ef0f4",
        "type": "comment",
        "z": "fbdc5aeae38a6415",
        "name": "Generar Dibujo",
        "info": "",
        "x": 160,
        "y": 860,
        "wires": []
    },
    {
        "id": "ee459efa11358aea",
        "type": "exec",
        "z": "fbdc5aeae38a6415",
        "command": "/home/pi/Documents/GitHub/contraespacios/Drawing/.venv/bin/python3 /home/pi/Documents/GitHub/contraespacios/Drawing/generate_drawing.py",
        "addpay": "payload",
        "append": "",
        "useSpawn": "false",
        "timer": "60",
        "winHide": false,
        "oldrc": false,
        "name": "",
        "x": 890,
        "y": 960,
        "wires": [
            [
                "0ae74d93438faf4a"
            ],
            [
                "58e394ce8d10a26d"
            ],
            []
        ]
    },
    {
        "id": "f19e251037337628",
        "type": "function",
        "z": "fbdc5aeae38a6415",
        "name": "preparar_generate_drawing",
        "func": "// preparar_generate_drawing\n// Salida 1: OLED\n// Salida 2: exec Drawing\n\nfunction sh(value) {\n    return \"'\" + String(value).replace(/'/g, \"'\\\\''\") + \"'\";\n}\n\nif (flow.get(\"drawing_busy\")) {\n    const oledBusy = {\n        payload: JSON.stringify({\n            type: \"screen\",\n            title: \"DIBUJO\",\n            message: \"Ya estoy generando...\"\n        }),\n        ip: \"127.0.0.1\",\n        host: \"127.0.0.1\",\n        port: 5006\n    };\n\n    return [oledBusy, null];\n}\n\nconst input = (msg.payload && typeof msg.payload === \"object\") ? msg.payload : {};\n\nconst session =\n    input.session_id ||\n    input.active_session ||\n    input.session ||\n    msg.session_id ||\n    flow.get(\"active_session\") ||\n    flow.get(\"current_session\") ||\n    \"S01\";\n\nflow.set(\"active_session\", session);\nflow.set(\"drawing_busy\", true);\nflow.set(\"drawing_session\", session);\n\nconst execMsg = {\n    session_id: session,\n    payload: [\n        \"--session\", sh(session),\n        \"--data-root\", sh(\"/home/pi/data\"),\n        \"--film-width-mm\", \"30\",\n        \"--film-height-mm\", \"32\",\n        \"--gcode-y-mode\", \"direct\",\n        \"--path-start-corner\", \"top_right\",\n        \"--landscape-bands\", \"4\",\n        \"--internal-lines\", \"3\",\n        \"--max-contours\", \"4\"\n    ].join(\" \")\n};\n\n// No mandamos status todavía para no brincar a pantalla de estado.\n// resultado_generate_drawing avisará cuando el dibujo y el G-code estén listos.\nreturn [null, execMsg];",
        "outputs": 2,
        "timeout": 0,
        "noerr": 0,
        "initialize": "",
        "finalize": "",
        "libs": [],
        "x": 200,
        "y": 900,
        "wires": [
            [
                "414875922b7d6e4e"
            ],
            [
                "ee459efa11358aea"
            ]
        ],
        "outputLabels": [
            "5006",
            "exec"
        ]
    },
    {
        "id": "0ae74d93438faf4a",
        "type": "function",
        "z": "fbdc5aeae38a6415",
        "name": "resultado_generate_drawing",
        "func": "// resultado_generate_drawing\n\nflow.set(\"drawing_busy\", false);\n\nlet result;\n\ntry {\n    result = JSON.parse(msg.payload);\n} catch (err) {\n    msg.payload = JSON.stringify({\n        type: \"status\",\n        step: \"drawing\",\n        state: \"error\",\n        message: \"JSON invalido\",\n        screen: \"status\",\n        command: \"show_status\"\n    });\n\n    msg.ip = \"127.0.0.1\";\n    msg.host = \"127.0.0.1\";\n    msg.port = 5006;\n\n    return msg;\n}\n\nconst sessionId =\n    result.session_id ||\n    msg.session_id ||\n    flow.get(\"drawing_session\") ||\n    flow.get(\"active_session\") ||\n    \"S01\";\n\nif (result.ok === true) {\n    flow.set(\"drawing_done\", true);\n    flow.set(\"session_has_drawing\", true);\n    flow.set(\"gcode_done\", true);\n    flow.set(\"session_has_gcode\", true);\n\n    msg.payload = JSON.stringify({\n        type: \"framework_state\",\n        session_id: sessionId,\n\n        drawing: true,\n        drawing_done: true,\n        session_has_drawing: true,\n\n        gcode: true,\n        gcode_done: true,\n        session_has_gcode: true,\n\n        screen: \"status\",\n        command: \"show_status\",\n\n        step: \"drawing\",\n        state: \"done\",\n        message: \"Dibujo generado\",\n        progress: 75,\n\n        svg: result.svg,\n        preview: result.preview,\n        gcode_path: result.gcode,\n        metadata: result.metadata,\n        generation_log: result.generation_log,\n        steps: result.process_steps_dir\n    });\n\n    msg.ip = \"127.0.0.1\";\n    msg.host = \"127.0.0.1\";\n    msg.port = 5006;\n\n    node.status({\n        fill: \"green\",\n        shape: \"dot\",\n        text: `${sessionId} dibujo + G-code OK`\n    });\n\n    return msg;\n}\n\nflow.set(\"drawing_done\", false);\nflow.set(\"session_has_drawing\", false);\nflow.set(\"gcode_done\", false);\nflow.set(\"session_has_gcode\", false);\n\nmsg.payload = JSON.stringify({\n    type: \"status\",\n    session_id: sessionId,\n\n    drawing: false,\n    drawing_done: false,\n    session_has_drawing: false,\n\n    gcode: false,\n    gcode_done: false,\n    session_has_gcode: false,\n\n    step: \"drawing\",\n    state: \"error\",\n    message: result.message || \"Error dibujo\",\n    screen: \"status\",\n    command: \"show_status\"\n});\n\nmsg.ip = \"127.0.0.1\";\nmsg.host = \"127.0.0.1\";\nmsg.port = 5006;\n\nnode.status({\n    fill: \"red\",\n    shape: \"ring\",\n    text: `${sessionId} error dibujo`\n});\n\nreturn msg;",
        "outputs": 1,
        "timeout": 0,
        "noerr": 0,
        "initialize": "",
        "finalize": "",
        "libs": [],
        "x": 1560,
        "y": 920,
        "wires": [
            [
                "414875922b7d6e4e"
            ]
        ]
    },
    {
        "id": "58e394ce8d10a26d",
        "type": "function",
        "z": "fbdc5aeae38a6415",
        "name": "error_generate_drawing",
        "func": "// error_generate_drawing\n// Maneja errores impresos por stderr\n\nflow.set(\"drawing_busy\", false);\n\nlet errorText = \"\";\n\nif (typeof msg.payload === \"string\") {\n    errorText = msg.payload;\n} else {\n    errorText = JSON.stringify(msg.payload);\n}\n\nnode.warn(errorText);\n\nmsg.payload = JSON.stringify({\n    type: \"oled\",\n    screen: \"drawing_error\",\n    line1: \"Error script\",\n    line2: errorText.slice(0, 18)\n});\n\nreturn msg;",
        "outputs": 1,
        "timeout": 0,
        "noerr": 0,
        "initialize": "",
        "finalize": "",
        "libs": [],
        "x": 1550,
        "y": 980,
        "wires": [
            [
                "414875922b7d6e4e"
            ]
        ]
    },
    {
        "id": "77815b21a67ab57d",
        "type": "comment",
        "z": "fbdc5aeae38a6415",
        "name": "Dibujar",
        "info": "",
        "x": 130,
        "y": 1040,
        "wires": []
    },
    {
        "id": "ca31b4fae4ded149",
        "type": "function",
        "z": "fbdc5aeae38a6415",
        "name": "preparar_execute_drawing",
        "func": "// preparar_execute_drawing\n// Salida 1: OLED\n// Salida 2: exec Filmic\n\nfunction sh(value) {\n    return \"'\" + String(value).replace(/'/g, \"'\\\\''\") + \"'\";\n}\n\nconst now = Date.now();\nconst startedAt = Number(flow.get(\"execution_started_at\") || 0);\nconst staleMs = 10 * 60 * 1000;\n\nif (flow.get(\"execution_busy\") === true && startedAt && (now - startedAt) < staleMs) {\n    const oledBusy = {\n        payload: JSON.stringify({\n            type: \"screen\",\n            title: \"DIBUJANDO\",\n            message: \"Ejecucion en curso\"\n        }),\n        ip: \"127.0.0.1\",\n        host: \"127.0.0.1\",\n        port: 5006\n    };\n\n    return [oledBusy, null];\n}\n\n// Si quedó un bloqueo viejo sin proceso activo, se limpia aquí.\nflow.set(\"execution_busy\", false);\nflow.set(\"execution_started_at\", 0);\n\nconst p = msg.payload || {};\n\nconst sessionId =\n    p.session_id ||\n    p.active_session ||\n    msg.session_id ||\n    flow.get(\"active_session\") ||\n    \"S01\";\n\nflow.set(\"active_session\", sessionId);\nflow.set(\"execution_busy\", true);\nflow.set(\"execution_started_at\", now);\nflow.set(\"execution_done\", false);\nflow.set(\"drawing_executed\", false);\n\nconst execMsg = {\n    session_id: sessionId,\n    payload: [\n        \"--session\", sh(sessionId),\n        \"--data-root\", sh(\"/home/pi/data\"),\n        \"--port\", sh(\"/dev/ttyACM0\"),\n        \"--homing\",\n        \"--calibrate-area\",\n        \"--calibrate-x-dir\", \"1\",\n        \"--calibrate-y-dir\", \"-1\",\n        \"--calibration-step-mm\", \"4\",\n        \"--calibration-fine-step-mm\", \"1\",\n        \"--calibration-backoff-mm\", \"6\",\n        \"--calibration-feed-mm-min\", \"350\",\n        \"--calibration-fine-feed-mm-min\", \"180\",\n        \"--fit-gcode-to-area\",\n        \"--fit-margin-mm\", \"1\",\n        \"--fit-mode\", \"uniform\",\n        \"--set-work-zero\",\n        \"--unlock\"\n    ].join(\" \")\n};\n\nreturn [null, execMsg];",
        "outputs": 2,
        "timeout": 0,
        "noerr": 0,
        "initialize": "",
        "finalize": "",
        "libs": [],
        "x": 200,
        "y": 1100,
        "wires": [
            [
                "414875922b7d6e4e"
            ],
            [
                "801bdcf8fec24aa6"
            ]
        ],
        "outputLabels": [
            "5006",
            "exec filmic"
        ]
    },
    {
        "id": "801bdcf8fec24aa6",
        "type": "exec",
        "z": "fbdc5aeae38a6415",
        "command": "/home/pi/Documents/GitHub/contraespacios/Filmic/.venv/bin/python3 /home/pi/Documents/GitHub/contraespacios/Filmic/execute_drawing.py",
        "addpay": "payload",
        "append": "",
        "useSpawn": "true",
        "timer": "",
        "winHide": false,
        "oldrc": false,
        "name": "",
        "x": 870,
        "y": 1120,
        "wires": [
            [
                "cd54b804694ba088"
            ],
            [
                "b0ae2bd80390c045"
            ],
            [
                "f0c0de_execute_rc"
            ]
        ]
    },
    {
        "id": "cd54b804694ba088",
        "type": "function",
        "z": "fbdc5aeae38a6415",
        "name": "resultado_execute_drawing",
        "func": "// resultado_execute_drawing\n// Procesa JSONL emitido por Filmic\n\nlet lines = [];\n\nif (typeof msg.payload === \"string\") {\n    lines = msg.payload.split(/\\r?\\n/).filter(Boolean);\n} else {\n    lines = [JSON.stringify(msg.payload)];\n}\n\nlet last = null;\n\nfor (const line of lines) {\n    try {\n        last = JSON.parse(line);\n    } catch (err) {\n        node.warn(\"Linea no JSON desde Filmic: \" + line);\n    }\n}\n\nif (!last) {\n    return null;\n}\n\nconst sessionId =\n    last.session_id ||\n    msg.session_id ||\n    flow.get(\"active_session\") ||\n    \"S01\";\n\nif (last.type === \"execute_progress\") {\n    msg.payload = JSON.stringify({\n        type: \"status\",\n        session_id: sessionId,\n        step: last.step || \"execute\",\n        state: last.state || \"running\",\n        message: last.message || \"Ejecutando\",\n        progress: last.progress || 0\n    });\n\n    msg.ip = \"127.0.0.1\";\n    msg.host = \"127.0.0.1\";\n    msg.port = 5006;\n\n    return msg;\n}\n\nif (last.ok === true && last.type === \"execute_result\") {\n    flow.set(\"execution_busy\", false);\nflow.set(\"execution_started_at\", 0);\n    flow.set(\"execution_done\", true);\n    flow.set(\"drawing_executed\", true);\n\n    msg.payload = JSON.stringify({\n        type: \"framework_state\",\n        session_id: sessionId,\n\n        drawing_executed: true,\n        execution_done: true,\n        executed: true,\n\n        screen: \"status\",\n        command: \"show_status\",\n\n        step: \"execute\",\n        state: \"done\",\n        message: \"Dibujo ejecutado\",\n        progress: 100,\n\n        calibration: last.calibration || null\n    });\n\n    msg.ip = \"127.0.0.1\";\n    msg.host = \"127.0.0.1\";\n    msg.port = 5006;\n\n    node.status({\n        fill: \"green\",\n        shape: \"dot\",\n        text: `${sessionId} ejecutado`\n    });\n\n    return msg;\n}\n\nif (last.ok === false) {\n    flow.set(\"execution_busy\", false);\nflow.set(\"execution_started_at\", 0);\n    flow.set(\"execution_done\", false);\n    flow.set(\"drawing_executed\", false);\n\n    msg.payload = JSON.stringify({\n        type: \"status\",\n        session_id: sessionId,\n        step: \"execute\",\n        state: \"error\",\n        message: last.message || last.error || \"Error ejecución\",\n        screen: \"status\",\n        command: \"show_status\"\n    });\n\n    msg.ip = \"127.0.0.1\";\n    msg.host = \"127.0.0.1\";\n    msg.port = 5006;\n\n    node.status({\n        fill: \"red\",\n        shape: \"ring\",\n        text: `${sessionId} error ejecución`\n    });\n\n    return msg;\n}\n\nreturn null;",
        "outputs": 1,
        "timeout": 0,
        "noerr": 0,
        "initialize": "",
        "finalize": "",
        "libs": [],
        "x": 1580,
        "y": 1100,
        "wires": [
            [
                "414875922b7d6e4e"
            ]
        ]
    },
    {
        "id": "b0ae2bd80390c045",
        "type": "function",
        "z": "fbdc5aeae38a6415",
        "name": "error_execute_drawing",
        "func": "// error_execute_drawing\n\nflow.set(\"execution_busy\", false);\nflow.set(\"execution_started_at\", 0);\nflow.set(\"execution_done\", false);\nflow.set(\"drawing_executed\", false);\n\nconst sessionId =\n    msg.session_id ||\n    flow.get(\"active_session\") ||\n    \"S01\";\n\nconst errorText =\n    typeof msg.payload === \"string\"\n        ? msg.payload\n        : JSON.stringify(msg.payload);\n\nnode.warn(errorText);\n\nmsg.payload = JSON.stringify({\n    type: \"status\",\n    session_id: sessionId,\n    step: \"execute\",\n    state: \"error\",\n    message: errorText.slice(0, 40),\n    screen: \"status\",\n    command: \"show_status\"\n});\n\nmsg.ip = \"127.0.0.1\";\nmsg.host = \"127.0.0.1\";\nmsg.port = 5006;\n\nreturn msg;",
        "outputs": 1,
        "timeout": 0,
        "noerr": 0,
        "initialize": "",
        "finalize": "",
        "libs": [],
        "x": 1560,
        "y": 1140,
        "wires": [
            [
                "414875922b7d6e4e"
            ]
        ]
    },
    {
        "id": "f0c0de_execute_rc",
        "type": "function",
        "z": "fbdc5aeae38a6415",
        "name": "fin_execute_drawing",
        "func": "// fin_execute_drawing\n// Tercer output del exec Filmic: código de salida.\n\nlet rc = null;\n\nif (typeof msg.payload === \"number\") {\n    rc = msg.payload;\n} else if (typeof msg.payload === \"string\" && msg.payload.trim() !== \"\") {\n    rc = Number(msg.payload.trim());\n} else if (msg.payload && typeof msg.payload === \"object\") {\n    rc = Number(\n        msg.payload.code ??\n        msg.payload.rc ??\n        msg.payload.returnCode ??\n        msg.payload.exitCode\n    );\n}\n\n// Si terminó bien, resultado_execute_drawing ya limpió estado y avisó a OLED.\nif (rc === 0) {\n    return null;\n}\n\nflow.set(\"execution_busy\", false);\nflow.set(\"execution_started_at\", 0);\nflow.set(\"execution_done\", false);\nflow.set(\"drawing_executed\", false);\n\nconst sessionId =\n    msg.session_id ||\n    flow.get(\"active_session\") ||\n    \"S01\";\n\nconst shown = Number.isFinite(rc) ? `Filmic salio con codigo ${rc}` : \"Filmic termino con error\";\n\nmsg.payload = JSON.stringify({\n    type: \"status\",\n    session_id: sessionId,\n    step: \"execute\",\n    state: \"error\",\n    message: shown,\n    screen: \"status\",\n    command: \"show_status\"\n});\n\nmsg.ip = \"127.0.0.1\";\nmsg.host = \"127.0.0.1\";\nmsg.port = 5006;\n\nnode.status({\n    fill: \"red\",\n    shape: \"ring\",\n    text: shown\n});\n\nreturn msg;",
        "outputs": 1,
        "timeout": 0,
        "noerr": 0,
        "initialize": "",
        "finalize": "",
        "libs": [],
        "x": 1560,
        "y": 1180,
        "wires": [
            [
                "414875922b7d6e4e"
            ]
        ]
    }
]
